async_messages/__init__.py
async_messages/messages.py
async_messages/middleware.py
django_async_messages_redux-0.4.1.dist-info/DESCRIPTION.rst
django_async_messages_redux-0.4.1.dist-info/METADATA
django_async_messages_redux-0.4.1.dist-info/RECORD
django_async_messages_redux-0.4.1.dist-info/WHEEL
django_async_messages_redux-0.4.1.dist-info/metadata.json
django_async_messages_redux-0.4.1.dist-info/top_level.txt
