Metadata-Version: 2.0
Name: django-async-messages-redux
Version: 0.4.1
Summary: Send asynchronous messages to users (eg from offline scripts). Useful for integration with Celery.
Home-page: https://github.com/maurizi/django-async-messages
Author: Michael Maurizi
Author-email: michael@maurizi.org
License: UNKNOWN
Platform: UNKNOWN
Requires-Dist: django (>=1.4)
